Workbook

Sheet Executive Summary
A1: IMS QA — Executive Summary
A3: Application | B3: https://erp.southerneleven.com (Southern IoT / R Suites)
A4: Tested | B4: 13 August 2026, single session, production with QA-labelled test data
A5: Baseline | B5: Inventory_Management_Requirements.docx
A6: Roles exercised | B6: General, Inventory Manager, Approver 1, Approver 2, Administrator — all five
A8: Verdict
B9: The build is substantially more capable than the requirements document describes, and the parts that are
B10: finished are well made — stock accounting, the borrow/return lifecycle, the approval chain and its audit
B11: trail are all better than specified. The defects that matter are concentrated in two places: date handling,
B12: and financial controls around the sanctioned amount. Neither is a design problem; both are bounded bugs.
A14: Fix before anyone relies on the figures
A15: D-014 Critical | B15: Every date is stored one day early, and shifts again on each save. Reproduced in requisition deadlines and borrowing return dates. Undermines the whole section 5 reminder flow.
A16: D-022 Critical | B16: An approver can sanction MORE than was requested, unbounded (15,000 -> 99,000 accepted). The inflated figure then sets the funding ceiling, so cash can be released against it.
A17: D-020 High | B17: The Expenses report counts rejected and unapproved requisitions as 'Approved', on a page that claims 'Figures always reconcile' and exports to Accounts.
A18: D-030 High | B18: The audit log shows 'Unknown actor' for nearly every action, including every approval and rejection.
A19: D-024 High | B19: Expenses CSV/PDF export returns the app's HTML shell with a .csv/.pdf filename. Fails silently. (The BOM PDF, by contrast, works.)
A20: D-028 High | B20: A BOM quantity equal to the full requisitioned amount silently clears the field — the most common case cannot be entered.
A21: D-023 High | B21: The section 4 approver delegate feature has no UI anywhere, though 'ON BEHALF OF' exists in the BOM data.
A23: Worth knowing
A24: Config, not code | B24: D-001 (no below-threshold requisition could be submitted) was an unassigned 'Sub-threshold approver' setting. Now assigned; the 1-approver path works.
A25: Doc, not code | B25: D-007 (15,000 exactly gets 2 approvers) is the product's documented rule — 'at or above'. The requirements doc's wording is what disagrees.
A26: Undocumented | B26: 14 substantial features exist that the requirements never mention: the IM review stage, sanctioned-vs-requested amounts, transportation cost, supporting documents, a full borrowing module, projects, quarantine, approval signatures, the Expenses report, configurable audit logging, and department-level approver overrides.
A28: Done well — do not regress
B29: Stock accounting reconciles at every step, including a damaged return going to Quarantine rather than back to stock.
B30: Rejection ends the request, skips the remaining approvers and cannot be reopened — exactly section 4.
B31: Self-approval is blocked outright, with a message that explains the fix.
B32: Either approver may act first, in both orders, with the outstanding approver always named.
B33: The BOM freezes its approval chain at generation and renders a real PDF.
B34: Over-funding, negative funding, negative quantities and prices, and past-dated thresholds are all rejected.
B35: Output encoding is clean; the browser console is error-free.
A37: Not covered
A38: NT-02 | B38: The approval-deadline reminder could not be triggered in-session (time-based). Verify separately.
A39: EX-03 | B39: The BOM PDF is valid and correctly typed, but its rendered figures were not compared line by line. One human eyeball recommended.
A40: D-013 | B40: Server-side per-role authorisation was not tested. UI blocking works and the API rejects unauthenticated calls, but per-endpoint role enforcement needs an API client and explicit authorisation.
A41: Scope | B41: No penetration testing, load testing or infrastructure review, by agreement.

Sheet Summary
A1: IMS QA — Test Execution Summary
A2: Southern IoT · https://erp.southerneleven.com
A3: Requirements source: Inventory_Management_Requirements.docx (R Suites)
A5: Overall
A6: Total test cases | B6: =COUNTA('Test Cases'!A2:A187) -> 186
A7: Pass | B7: =COUNTIF('Test Cases'!I2:I187,"Pass") -> 90
A8: Fail | B8: =COUNTIF('Test Cases'!I2:I187,"Fail") -> 32
A9: Blocked | B9: =COUNTIF('Test Cases'!I2:I187,"Blocked") -> 5
A10: N/A | B10: =COUNTIF('Test Cases'!I2:I187,"N/A") -> 0
A11: Observation | B11: =COUNTIF('Test Cases'!I2:I187,"Observation") -> 26
A12: Not run | B12: =COUNTIF('Test Cases'!I2:I187,"Not run") -> 33
A13: Executed | B13: =B7+B8+B9+B11 -> 153
A14: Pass rate (of executed) | B14: =IFERROR(B7/B13,0) -> 0.58823529
A16: By severity (failures)
A17: Critical | B17: =COUNTIFS('Test Cases'!J2:J187,"Critical",'Test Cases'!I2:I187,"Fail") -> 6
A18: High | B18: =COUNTIFS('Test Cases'!J2:J187,"High",'Test Cases'!I2:I187,"Fail") -> 6
A19: Medium | B19: =COUNTIFS('Test Cases'!J2:J187,"Medium",'Test Cases'!I2:I187,"Fail") -> 10
A20: Low | B20: =COUNTIFS('Test Cases'!J2:J187,"Low",'Test Cases'!I2:I187,"Fail") -> 4
A21: Cosmetic | B21: =COUNTIFS('Test Cases'!J2:J187,"Cosmetic",'Test Cases'!I2:I187,"Fail") -> 6
A24: By area
A25: Area | B25: Total | C25: Pass | D25: Fail | E25: Not run
A26: Access control | B26: =COUNTIF('Test Cases'!C2:C187,A26) -> 13 | C26: =COUNTIFS('Test Cases'!C2:C187,A26,'Test Cases'!I2:I187,"Pass") -> 9 | D26: =COUNTIFS('Test Cases'!C2:C187,A26,'Test Cases'!I2:I187,"Fail") -> 1 | E26: =COUNTIFS('Test Cases'!C2:C187,A26,'Test Cases'!I2:I187,"Not run") -> 1
A27: Request form | B27: =COUNTIF('Test Cases'!C2:C187,A27) -> 34 | C27: =COUNTIFS('Test Cases'!C2:C187,A27,'Test Cases'!I2:I187,"Pass") -> 15 | D27: =COUNTIFS('Test Cases'!C2:C187,A27,'Test Cases'!I2:I187,"Fail") -> 8 | E27: =COUNTIFS('Test Cases'!C2:C187,A27,'Test Cases'!I2:I187,"Not run") -> 10
A28: Approval flow | B28: =COUNTIF('Test Cases'!C2:C187,A28) -> 28 | C28: =COUNTIFS('Test Cases'!C2:C187,A28,'Test Cases'!I2:I187,"Pass") -> 16 | D28: =COUNTIFS('Test Cases'!C2:C187,A28,'Test Cases'!I2:I187,"Fail") -> 4 | E28: =COUNTIFS('Test Cases'!C2:C187,A28,'Test Cases'!I2:I187,"Not run") -> 0
A29: Notifications | B29: =COUNTIF('Test Cases'!C2:C187,A29) -> 9 | C29: =COUNTIFS('Test Cases'!C2:C187,A29,'Test Cases'!I2:I187,"Pass") -> 2 | D29: =COUNTIFS('Test Cases'!C2:C187,A29,'Test Cases'!I2:I187,"Fail") -> 0 | E29: =COUNTIFS('Test Cases'!C2:C187,A29,'Test Cases'!I2:I187,"Not run") -> 7
A30: Fund logging | B30: =COUNTIF('Test Cases'!C2:C187,A30) -> 13 | C30: =COUNTIFS('Test Cases'!C2:C187,A30,'Test Cases'!I2:I187,"Pass") -> 11 | D30: =COUNTIFS('Test Cases'!C2:C187,A30,'Test Cases'!I2:I187,"Fail") -> 1 | E30: =COUNTIFS('Test Cases'!C2:C187,A30,'Test Cases'!I2:I187,"Not run") -> 1
A31: Inventory | B31: =COUNTIF('Test Cases'!C2:C187,A31) -> 17 | C31: =COUNTIFS('Test Cases'!C2:C187,A31,'Test Cases'!I2:I187,"Pass") -> 8 | D31: =COUNTIFS('Test Cases'!C2:C187,A31,'Test Cases'!I2:I187,"Fail") -> 0 | E31: =COUNTIFS('Test Cases'!C2:C187,A31,'Test Cases'!I2:I187,"Not run") -> 6
A32: Returns | B32: =COUNTIF('Test Cases'!C2:C187,A32) -> 11 | C32: =COUNTIFS('Test Cases'!C2:C187,A32,'Test Cases'!I2:I187,"Pass") -> 8 | D32: =COUNTIFS('Test Cases'!C2:C187,A32,'Test Cases'!I2:I187,"Fail") -> 1 | E32: =COUNTIFS('Test Cases'!C2:C187,A32,'Test Cases'!I2:I187,"Not run") -> 2
A33: BOM | B33: =COUNTIF('Test Cases'!C2:C187,A33) -> 14 | C33: =COUNTIFS('Test Cases'!C2:C187,A33,'Test Cases'!I2:I187,"Pass") -> 8 | D33: =COUNTIFS('Test Cases'!C2:C187,A33,'Test Cases'!I2:I187,"Fail") -> 4 | E33: =COUNTIFS('Test Cases'!C2:C187,A33,'Test Cases'!I2:I187,"Not run") -> 0
A34: Export | B34: =COUNTIF('Test Cases'!C2:C187,A34) -> 10 | C34: =COUNTIFS('Test Cases'!C2:C187,A34,'Test Cases'!I2:I187,"Pass") -> 3 | D34: =COUNTIFS('Test Cases'!C2:C187,A34,'Test Cases'!I2:I187,"Fail") -> 4 | E34: =COUNTIFS('Test Cases'!C2:C187,A34,'Test Cases'!I2:I187,"Not run") -> 1
A35: Admin config | B35: =COUNTIF('Test Cases'!C2:C187,A35) -> 9 | C35: =COUNTIFS('Test Cases'!C2:C187,A35,'Test Cases'!I2:I187,"Pass") -> 7 | D35: =COUNTIFS('Test Cases'!C2:C187,A35,'Test Cases'!I2:I187,"Fail") -> 1 | E35: =COUNTIFS('Test Cases'!C2:C187,A35,'Test Cases'!I2:I187,"Not run") -> 0
A36: UI/UX | B36: =COUNTIF('Test Cases'!C2:C187,A36) -> 18 | C36: =COUNTIFS('Test Cases'!C2:C187,A36,'Test Cases'!I2:I187,"Pass") -> 3 | D36: =COUNTIFS('Test Cases'!C2:C187,A36,'Test Cases'!I2:I187,"Fail") -> 8 | E36: =COUNTIFS('Test Cases'!C2:C187,A36,'Test Cases'!I2:I187,"Not run") -> 5
A37: Doc gap | B37: =COUNTIF('Test Cases'!C2:C187,A37) -> 10 | C37: =COUNTIFS('Test Cases'!C2:C187,A37,'Test Cases'!I2:I187,"Pass") -> 0 | D37: =COUNTIFS('Test Cases'!C2:C187,A37,'Test Cases'!I2:I187,"Fail") -> 0 | E37: =COUNTIFS('Test Cases'!C2:C187,A37,'Test Cases'!I2:I187,"Not run") -> 0

Sheet Scope & Approach
A1: IMS QA — Scope & Approach
A3: Application | B3: https://erp.southerneleven.com
A4: Environment | B4: Production, with clearly-labelled test data (agreed with product owner)
A5: Requirements baseline | B5: Inventory_Management_Requirements.docx — R Suites
A6: Roles under test | B6: General, Approver A, Approver B, Delegate, Inventory Manager, Admin
A8: In scope
A9: 1 | B9: Functional verification of every requirement in sections 2-11 of the requirements document
A10: 2 | B10: Negative and boundary testing (blank input, zero/negative values, threshold boundary at 14,999 / 15,000 / 15,001, over-funding, double approval, past deadlines)
A11: 3 | B11: UI/UX and usability review (labelling, validation messaging, formatting consistency, responsive layout, keyboard access, console errors)
A12: 4 | B12: Role-based access control: confirming each role cannot reach screens or records outside its remit, including direct-URL and object-ID access
A13: 5 | B13: Requirements-vs-build gap analysis (features built but undocumented, and requirements not yet built)
A15: Out of scope
A16: 1 | B16: Penetration testing, authentication bypass, injection attacks or any form of exploitation. Access control is verified only by navigating as an authorised but incorrectly-privileged user.
A17: 2 | B17: Load, stress and performance testing
A18: 3 | B18: Server, database, infrastructure and backup verification
A19: 4 | B19: Deletion of any pre-existing production record
A21: Method
A22: 1 | B22: Each test case is executed against the live application through the browser, as the role named in the Role column.
A23: 2 | B23: Status is recorded as Pass, Fail, Blocked, N/A or Observation. 'Observation' is used where behaviour is defensible but the requirement is silent.
A24: 3 | B24: Every Fail is written up in the Defect Log with reproduction steps and severity.
A25: 4 | B25: Every record created is logged in Test Data & Cleanup for removal after sign-off.
A27: Severity definitions
A28: Critical | B28: Data loss, incorrect financial figures, or a role able to act outside its permissions
A29: High | B29: A documented requirement does not work; no workaround
A30: Medium | B30: A requirement works incorrectly in some cases, or has an awkward workaround
A31: Low | B31: Minor functional or usability issue with little operational impact
A32: Cosmetic | B32: Wording, formatting or alignment only

Sheet Test Cases
A1: Test ID | B1: Req Ref | C1: Area | D1: Role | E1: Type | F1: Test Steps | G1: Expected Result | H1: Actual Result | I1: Status | J1: Severity | K1: Notes
A2: AC-01 | B2: §2 | C2: Access control | D2: General | E2: Access | F2: As General, open /approvals (or approver route) directly by URL | G2: Access denied / redirect. No approval queue rendered. | H2: /approvals returns 'Not allowed — Your account does not have permission to view this page.' | I2: Pass
A3: AC-02 | B3: §2, §6 | C3: Access control | D3: General | E3: Access | F3: As General, open the Inventory Manager fund-logging route directly by URL | G3: Access denied / redirect. | H3: /boms and /inventory/locations both return 'Not allowed'. | I3: Pass
A4: AC-03 | B4: §11 | C4: Access control | D4: General | E4: Access | F4: As General, open the admin settings / threshold route directly by URL | G4: Access denied / redirect. | H4: /admin/settings, /admin/users, /admin/audit-log all return 'Not allowed'. | I4: Pass
A5: AC-04 | B5: §2 | C5: Access control | D5: General | E5: Access | F5: On My requisitions, confirm only the logged-in user's own requests are listed | G5: No other requester's requisitions visible. | H5: Only Gina General's own requisitions listed (REQ-000001 to 000007, all hers). | I5: Pass | K5: No other requester's records leaked into the list.
A6: AC-05 | B6: §4 | C6: Access control | D6: General | E6: Negative | F6: Submit a request as Gina General, then check whether she can approve it herself | G6: Requester cannot approve own request. | H6: Ayesha (an approver) raised a 25,000 requisition and tried to submit it. Blocked: 'You are the approver for this requisition, and nobody is configured to approve it in your place. An administrator must assign another approver in Settings before you can submit this.' | I6: Pass | K6: Self-approval is explicitly prevented. The message also reveals a substitute-approver concept in admin Settings - see AP-14.
A7: AC-06 | B7: §2 | C7: Access control | D7: All | E7: Functional | F7: Compare the role badge on Dashboard against the nav items actually rendered | G7: Badge matches the permission set; no nav item shown that the role cannot use. | H7: Role badges match the rendered navigation for all five accounts. Admin sees an ADMINISTRATION section (Users, Departments, Settings, Audit log) that no other role sees. | I7: Pass
A8: AC-07 | B8: §2 | C8: Access control | D8: Anon | E8: Access | F8: Log out, then open a deep URL (e.g. /requisitions) | G8: Redirected to /login; no data leaked. | H8: Not executed — requires logging out, which would end the session hand-over. | I8: Not run | K8: Retest when convenient.
A9: AC-08 | B9: §2 | C9: Access control | D9: General | E9: Access | F9: As General, attempt to open another user's requisition by guessing its reference/ID in the URL | G9: Access denied. Object-level authorisation enforced, not just menu hiding. | H9: Requisition IDs are UUIDs, so guessing another user's record is not feasible through the UI. | I9: Blocked | K9: Server-side object authorisation must be verified by the dev team with an API client. See D-013.
A10: AC-09 | B10: §2 | C10: Access control | D10: Approver | E10: Access | F10: As Approver, confirm Inventory Manager screens (funds, BOM, returns) are not reachable | G10: Access denied / not rendered. | H10: As Imran (Inventory Manager), /admin/settings returns 'Not allowed'. IM nav exposes only Approvals, Expenses, Borrowing, All requisitions, Categories, Locations and Bills of Materials. | I10: Pass
A11: AC-10 | B11: §2 | C11: Access control | D11: Inv. Manager | E11: Access | F11: As Inventory Manager, confirm the approval action is not available on a pending request | G11: Cannot approve/reject unless also an assigned approver. | H11: The IM is a first-class approval stage, not an exception - every requisition goes to IM review before Approver 1 and 2. | I11: Observation | K11: Undocumented workflow step; see DG-11.
A12: RF-01 | B12: §3 | C12: Request form | D12: General | E12: Functional | F12: Open New requisition; confirm per-request fields exist: Department, Project, Urgency, Approval deadline, Reason | G12: All five present and set once per request. | H12: Department, Project, Urgency, Approval deadline and Reason all present, set once per request. | I12: Pass
A13: RF-02 | B13: §3 | C13: Request form | D13: General | E13: Functional | F13: Confirm each item line captures its own Item name and Quantity | G13: Per-line name + quantity present. | H13: Each item line has its own Item name and Quantity, plus Unit price. | I13: Pass
A14: RF-03 | B14: §3 | C14: Request form | D14: General | E14: Functional | F14: Click Add item three times | G14: Three additional independent item lines added. | H14: Add item creates independent lines; tested to 2 lines, focus moves to the new line. | I14: Pass
A15: RF-04 | B15: §3 | C15: Request form | D15: General | E15: Functional | F15: Remove a middle item line via the bin icon | G15: Correct line removed; remaining lines and totals re-index correctly. | I15: Not run
A16: RF-05 | B16: §3 | C16: Request form | D16: General | E16: Calculation | F16: Enter Qty 3, Unit price 2,500 | G16: Line total = 7,500.00 | H16: Qty 3 x 2,500 = Line total 7,500.00 | I16: Pass
A17: RF-06 | B17: §3 | C17: Request form | D17: General | E17: Calculation | F17: Add a second line Qty 2 @ 1,000 | G17: Items total = 9,500.00 (sum of line totals). | H17: Added 2 x 1,000; Items total = 9,500.00 | I17: Pass
A18: RF-07 | B18: §3 | C18: Request form | D18: General | E18: Calculation | F18: Add Transportation cost 500 | G18: Requested amount = Items total + Transportation = 10,000.00 | H18: Transportation 500 -> Requested amount 10,000.00 | I18: Pass | K18: Transportation correctly rolls into Requested amount.
A19: RF-08 | B19: §3 | C19: Request form | D19: General | E19: Functional | F19: Type in the Item field and check catalogue suggestions appear | G19: Catalogue items (e.g. Lenovo ThinkPad T14) offered from inventory. | H19: No catalogue picker exists. Typing 'Think' or 'Lenovo' produced no suggestions. DOM shows a plain <input autocomplete='off'> with no datalist, no combobox role, and 0 datalist elements on the page. | I19: Fail | J19: Medium | K19: D-002. Helper text 'Pick from the catalogue' and the permanent 'Not in the catalogue' badge promise a feature that is not wired up.
A20: RF-09 | B20: §3 | C20: Request form | D20: General | E20: Functional | F20: Type a free-text item not in the catalogue | G20: Accepted; 'Not in the catalogue' badge shown. | H20: Free-text item accepted; 'Not in the catalogue' badge shown. | I20: Pass | K20: Badge is always shown because no catalogue lookup exists (see RF-08).
A21: RF-10 | B21: §3 | C21: Request form | D21: General | E21: Functional | F21: Click Save draft | G21: Saved; appears under the Drafts filter on My requisitions. | H21: Save draft works; draft appears in the list and under the Drafts filter. | I21: Pass
A22: RF-11 | B22: §3 | C22: Request form | D22: General | E22: Functional | F22: Reopen the saved draft and change quantity, save again | G22: Edits persist correctly. | H22: Draft reopens with Urgency, Reason and all item lines intact, but Department and Project both reset to 'No department'/'No project' in the form even though the record still holds Engineering/Test. | I22: Fail | J22: Medium | K22: D-004. Values are preserved on save, so this is a display defect, not data loss - but it invites the user to think they were never set.
A23: RF-12 | B23: §3 | C23: Request form | D23: General | E23: Functional | F23: Submit for approval | G23: Status becomes Awaiting approval; reference REQ-nnnnnn assigned. | H23: Submit created REQ-000003 with status 'With the Inventory Manager'. | I23: Pass
A24: RF-13 | B24: §3 | C24: Request form | D24: General | E24: Functional | F24: Attach a supporting document (PDF), then submit | G24: File uploads, is listed on the request, and is downloadable by approvers. | I24: Not run
A25: RF-14 | B25: §3 | C25: Request form | D25: General | E25: Functional | F25: Confirm Project selected on the request carries through to the BOM later | G25: Project feeds the BOM (verified again in BM-02). | I25: Not run
A26: RF-N01 | B26: §3 | C26: Request form | D26: General | E26: Negative | F26: Click Submit for approval on a completely empty form | G26: Blocked with clear field-level validation; no request created. | H26: Submission blocked. Quantity and Unit price show 'Required'; Item shows 'String must contain at least 1 character(s)'. | I26: Pass | J26: Low | K26: Blocking works, but the Item message is a raw validation-library string. See D-005.
A27: RF-N02 | B27: §3 | C27: Request form | D27: General | E27: Negative | F27: Fill request details but leave all item lines blank, then submit | G27: Blocked — a request must contain at least one item. | H27: Covered by RF-N01 - the single blank item line blocks submission. | I27: Pass
A28: RF-N03 | B28: §3 | C28: Request form | D28: General | E28: Negative | F28: Set Quantity = 0 | G28: Rejected or flagged; a zero-quantity line should not be submittable. | I28: Not run
A29: RF-N04 | B29: §3 | C29: Request form | D29: General | E29: Negative | F29: Set Quantity = -5 | G29: Rejected. Negative quantity must not be accepted. | H29: Quantity -5 rejected: 'Number must be greater than 0'. | I29: Pass
A30: RF-N05 | B30: §3 | C30: Request form | D30: General | E30: Negative | F30: Set Quantity = 2.5 | G30: Defined behaviour: either rejected or handled consistently in totals and BOM. | I30: Not run
A31: RF-N06 | B31: §3 | C31: Request form | D31: General | E31: Negative | F31: Set Unit price = -1000 | G31: Rejected. Negative price must not reduce the request total. | H31: Unit price -1000 rejected: 'Number must be greater than or equal to 0'. | I31: Pass
A32: RF-N07 | B32: §3 | C32: Request form | D32: General | E32: Edge | F32: Set Unit price = 0 with Qty 1 and submit | G32: Defined behaviour; note which approval path a 0.00 request takes. | I32: Not run
A33: RF-N08 | B33: §3, §5 | C33: Request form | D33: General | E33: Negative | F33: Set Approval deadline to yesterday and submit | G33: Blocked — helper text states 'Pick today or later'. | H33: Approval deadline set to 2026-08-01 (12 days past). No validation error. REQ-000006 submitted successfully and was immediately tagged 'Overdue'. | I33: Fail | J33: Medium | K33: D-003. Helper text says 'Pick today or later' but nothing enforces it. A request can be created already overdue, firing the section 5 reminder at submit time.
A34: RF-N09 | B34: §3 | C34: Request form | D34: General | E34: Edge | F34: Enter Qty 999999999 and Unit price 999999999 | G34: No overflow, no scientific notation, no rounding corruption in the stored total. | H34: 99,999,999,999 rejected on submit: 'Number must be less than or equal to 1000000000'. No overflow. | I34: Pass | J34: Cosmetic | K34: Cap works. The message prints the bound unformatted (1000000000) and only fires on submit, while the Total meanwhile displays the invalid figure.
A35: RF-N10 | B35: §3 | C35: Request form | D35: General | E35: Edge | F35: Paste a 5,000-character string into Reason | G35: Either accepted and displayed intact, or limited with a clear message. No truncation without warning. | I35: Not run
A36: RF-N11 | B36: §3 | C36: Request form | D36: General | E36: Edge | F36: Enter the literal text <b>QA-TEST</b> in Item name and Reason, submit, then view the request | G36: Rendered as literal text on the detail page, not as HTML. Output encoding check only. | H36: Item name '<b>QA-TEST-Encoding</b>' stored and rendered as literal text on REQ-000007. No <b> elements in the DOM. | I36: Pass | K36: Output encoding is correct.
A37: RF-N12 | B37: §3 | C37: Request form | D37: General | E37: Negative | F37: Submit leaving Department = 'No department' and Project = 'No project' | G37: Defined behaviour. Note: doc §3 implies both are required per request. | H37: REQ-000003 submitted with no Department, no Project, no Reason and no Approval deadline. All accepted. | I37: Observation | J37: Medium | K37: D-006. Doc section 5's reminder flow depends on the deadline; a requisition with no deadline can never trigger it.
A38: RF-N13 | B38: §3 | C38: Request form | D38: General | E38: Edge | F38: Add the same catalogue item on two separate lines | G38: Defined behaviour: merged, or kept separate and totalled correctly. | I38: Not run
A39: RF-N14 | B39: §3 | C39: Request form | D39: General | E39: Edge | F39: Enter Transportation amount with no items | G39: Requested amount reflects transport only; note whether this is allowed. | I39: Not run
A40: RF-N15 | B40: §3 | C40: Request form | D40: General | E40: Edge | F40: Start filling the form, navigate away, come back | G40: Either the draft is preserved or the user is warned about unsaved changes. | I40: Not run
A41: AP-01 | B41: §4 | C41: Approval flow | D41: General/Approver | E41: Functional | F41: Submit a request totalling 10,000 BDT (below 15,000) | G41: Exactly 1 approver assigned. | H41: After assigning the sub-threshold approver, REQ-000009 at 10,000 submitted successfully with APPROVERS REQUIRED 1 and Approver 1 = Ayesha Approver. No Approver 2 slot appeared. | I41: Pass | K41: Unblocked by fixing the configuration - see D-001.
A42: AP-02 | B42: §4 | C42: Approval flow | D42: General/Approver | E42: Functional | F42: Submit a request totalling 27,700 BDT (above 15,000) | G42: Exactly 2 approvers assigned. | H42: REQ-000006 at 20,000 -> APPROVERS REQUIRED 2 (Ayesha Approver, Farhan Finance). | I42: Pass
A43: AP-03 | B43: §4 | C43: Approval flow | D43: General/Approver | E43: Boundary | F43: Submit a request totalling exactly 15,000.00 BDT | G43: Per doc ('above the threshold'), 15,000 is NOT above — expect 1 approver. Confirm intended. | H43: REQUIREMENTS DISCREPANCY, not a code defect. The Settings help text reads 'Requisitions AT OR ABOVE this amount need the higher number of approvers', so >= is deliberate and documented in the product. The requirements doc says 'above the threshold'. | I43: Observation | K43: Reclassified from Fail. Update the requirements doc, or change the rule - a product decision, not a bug.
A44: AP-04 | B44: §4 | C44: Approval flow | D44: General/Approver | E44: Boundary | F44: Submit a request totalling 15,001 BDT | G44: 2 approvers assigned. | H44: REQ-000005 at 15,100 -> 2 approvers. | I44: Pass
A45: AP-05 | B45: §4 | C45: Approval flow | D45: General/Approver | E45: Boundary | F45: Submit a request totalling 14,999 BDT | G45: 1 approver assigned. | H45: 14,999 is treated as below threshold and now routes to exactly 1 approver. | I45: Pass
A46: AP-06 | B46: §4 | C46: Approval flow | D46: General/Approver | E46: Boundary | F46: Submit items of 14,800 + Transportation 300 (= 15,100) | G46: Confirm whether the threshold is applied to Requested amount incl. transport. Doc is silent — flag either way. | H46: ANSWERED: items 14,800 + transport 300 = 15,100 -> 2 approvers. The threshold is applied to the transport-inclusive Requested amount, not the items total. | I46: Observation | K46: D-008. Not specified in the doc. Means transportation cost can move a request across the approval threshold.
A47: AP-07 | B47: §4 | C47: Approval flow | D47: Approver | E47: Functional | F47: On a 2-approver request, have Approver B approve first, then Approver A | G47: No fixed sequence — both orders accepted. | H47: Fully confirmed in both directions. On REQ-000003 Ayesha (Approver 1) acted first; on REQ-000005 and REQ-000001 Farhan (Approver 2) acted first. In every case the request stayed 'Awaiting approval' until the second approver signed. | I47: Pass
A48: AP-08 | B48: §4 | C48: Approval flow | D48: Approver | E48: Functional | F48: On a 2-approver request, Approver A rejects while B has not responded | G48: Whole request immediately Rejected. B's response not required. | H48: IM rejected REQ-000006. Status became Rejected, and both Approver 1 and Approver 2 were marked 'Skipped'. Confirmation dialog warned: 'Rejecting ends the whole request. The other approvers will not be asked, and it cannot be reopened.' | I48: Pass | K48: Behaves exactly as doc section 4 requires. Still to verify at the Approver 1 / Approver 2 stage.
A49: AP-09 | B49: §4 | C49: Approval flow | D49: Approver | E49: Functional | F49: On a 2-approver request, both approvers approve | G49: Status becomes Approved. | H49: Both approvers approved REQ-000003 -> status Approved. Also verified on REQ-000005 and REQ-000001. | I49: Pass
A50: AP-10 | B50: §4 | C50: Approval flow | D50: Approver | E50: Functional | F50: On a 2-approver request, only Approver A approves | G50: Status stays Awaiting approval; outstanding approver clearly indicated. | H50: After Ayesha approved REQ-000003, status remained 'Awaiting approval', Approver 1 showed 'Approved by 8/13/2026, 2:20:39 PM' and Approver 2 remained 'Waiting on'. | I50: Pass
A51: AP-11 | B51: §4 | C51: Approval flow | D51: Approver | E51: Functional | F51: As Approver A, view a part-approved request | G51: Can see which assigned approver(s) have not yet responded, by name. | H51: The Progress panel names each approver, their designation, and their state (Waiting on / Not reached yet / Approved by / Skipped) with timestamps. | I51: Pass | K51: Exceeds the requirement.
A52: AP-12 | B52: §4 | C52: Approval flow | D52: Approver | E52: Negative | F52: After approving, attempt to approve or reject the same request again | G52: Blocked; action no longer available. | H52: Once Ayesha had approved, the Approve and Reject controls were replaced by a single 'Withdraw approval' action. She could not approve twice. | I52: Pass | K52: Note the withdraw capability itself - see YY-03.
A53: AP-13 | B53: §4 | C53: Approval flow | D53: Approver | E53: Negative | F53: Attempt to approve a request that is already Rejected | G53: Blocked; terminal state is final. | H53: Once REQ-000006 was Rejected, no Approve or Reject control remained on the record. | I53: Pass
A54: AP-14 | B54: §4 | C54: Approval flow | D54: Approver | E54: Functional | F54: Approver A toggles ON a delegate, then the delegate opens the pending request | G54: Delegate can approve/reject on A's behalf. | H54: CONFIRMED ABSENT across every surface: the approver's own account page, the admin Edit user form (Full name, Email, Designation, Department, Roles only), and admin Settings (which offers only sub-threshold approver and the two approver slots). No delegate route exists in the app. | I54: Fail | J54: High | K54: D-023 stands. Note the BOM's frozen approval chain has an 'ON BEHALF OF' column, so delegation appears modelled in the data with no UI to drive it.
A55: AP-15 | B55: §4 | C55: Approval flow | D55: Approver | E55: Functional | F55: Delegate approves; inspect the request history | G55: Action attributed to the delegate acting for Approver A — not silently recorded as A. | H55: Cannot execute - no delegate mechanism available to the approver. | I55: Blocked | K55: Depends on D-023.
A56: AP-16 | B56: §4 | C56: Approval flow | D56: Approver | E56: Functional | F56: Approver A toggles the delegate OFF, delegate reopens the request | G56: Delegate can no longer act. | H56: Cannot execute - no delegate mechanism available to the approver. | I56: Blocked | K56: Depends on D-023.
A57: AP-17 | B57: §4 | C57: Approval flow | D57: Approver | E57: Negative | F57: Delegate attempts to approve a request where they are neither approver nor delegate | G57: Blocked. | H57: Cannot execute - no delegate mechanism available to the approver. | I57: Blocked | K57: Depends on D-023.
A58: AP-18 | B58: §4 | C58: Approval flow | D58: General | E58: Functional | F58: After submitting, attempt to edit amounts or the approver list | G58: Blocked — UI states 'Once submitted the amounts and the approver list are fixed'. | H58: The requester cannot alter amounts after submission, and 'Threshold at submit' is stamped on the record. However an approver CAN change the sanctioned amount afterwards - see ZZ-01. | I58: Observation | K58: Partially holds. The approver list is fixed; the amount is not.
A59: AP-19 | B59: §4, §11 | C59: Approval flow | D59: Admin | E59: Regression | F59: Change the threshold to 5,000, then open a pre-existing 10,000 request | G59: Existing request keeps its original approver list; change is not retroactive. | H59: Threshold raised to 20,000 then restored. REQ-000009 still reads 'Threshold at submit: 15,000' with 1 approver; earlier requisitions likewise kept their original stamp. Changes are not retroactive. | I59: Pass | K59: Well designed - the threshold is snapshotted per requisition.
A60: AP-20 | B60: §4 | C60: Approval flow | D60: Approver | E60: Functional | F60: Reject a request and check whether a rejection reason is captured | G60: Reason captured and shown to the requester (doc §5 requires notification; reason is good practice). | H60: Rejection captured a free-text note, surfaced to the requester via a 'See why' link on the Progress panel. | I60: Pass | K60: Optional rather than mandatory - consider requiring it.
A61: AP-21 | B61: §4 | C61: Approval flow | D61: Approver | E61: Functional | F61: Confirm the same person is not assigned twice as both approvers on an above-threshold request | G61: Two distinct approvers. | H61: Approver 1 (Ayesha Approver) and Approver 2 (Farhan Finance) are distinct named users. | I61: Pass
A62: NT-01 | B62: §5 | C62: Notifications | D62: Approver | E62: Functional | F62: Submit a request, then open the bell icon as the assigned approver | G62: New pending-approval notification present. | I62: Not run
A63: NT-02 | B63: §5 | C63: Notifications | D63: Approver | E63: Functional | F63: Create a request with the approval deadline set to today; let the deadline pass (or use the earliest reproducible trigger) | G63: Approver is pinged with a reminder. Record the exact trigger time and mechanism. | H63: Not executed - the reminder is triggered by the approval deadline passing, which could not be forced within the session. Note REQ-000006 was tagged 'Overdue' immediately on submission with a past deadline, so the overdue evaluation itself works. | I63: Not run | K63: Needs either a scheduled-job run or a manual trigger. Recommend verifying separately.
A64: NT-03 | B64: §5 | C64: Notifications | D64: General | E64: Functional | F64: Have an approver reject a request; check the requester's notifications | G64: Original requester is notified of the rejection. | H64: On rejection the system confirmed 'Rejected. The requester has been told.' | I64: Pass | K64: Confirmed from the actor's side; still to be confirmed in Gina's own notification list.
A65: NT-04 | B65: §5 | C65: Notifications | D65: General | E65: Functional | F65: Have a request fully approved; check the requester's notifications | G65: Note whether an approval notification exists. Not required by the doc — record as observation. | I65: Not run
A66: NT-05 | B66: §5 | C66: Notifications | D66: All | E66: Functional | F66: Check the bell badge count against the number of unread items | G66: Count is accurate; clears correctly once read. | H66: Bell showed a '6 unread notifications' badge as Imran, and the panel listed items with timestamps. | I66: Pass
A67: NT-06 | B67: §5 | C67: Notifications | D67: All | E67: Functional | F67: Click a notification | G67: Deep-links to the correct requisition. | H67: Not fully executed. | I67: Not run
A68: NT-07 | B68: §5 | C68: Notifications | D68: Approver | E68: Negative | F68: Let a deadline pass on a request that is already approved or rejected | G68: No reminder sent for a settled request. | I68: Not run
A69: NT-08 | B69: §5 | C69: Notifications | D69: Approver | E69: Edge | F69: Check whether the deadline reminder repeats or fires once | G69: Behaviour is defined and not a repeating spam loop. Doc says 'pinged' — clarify intent. | I69: Not run
A70: NT-09 | B70: §5 | C70: Notifications | D70: All | E70: Functional | F70: Determine the delivery channel (in-app only, email, or both) | G70: Channel documented. Doc §5 does not specify — confirm with product owner. | I70: Not run
A71: FL-01 | B71: §6 | C71: Fund logging | D71: Inv. Manager | E71: Functional | F71: Open an approved request and log funds received | G71: Funds recorded against that specific requisition. | H71: Recorded money received against REQ-000003 after sending it to Accounts. Receipts are captured with amount, date received, reference and note. | I71: Pass
A72: FL-02 | B72: §6 | C72: Fund logging | D72: Inv. Manager | E72: Functional | F72: Inspect the request after funding | G72: Requested amount, approved amount and funded amount are all visible and distinct. | H72: The Money and purchasing panel shows Approved, Funded, Spent, Transportation, Returned to Accounts and Unspent side by side, plus itemised RECEIPTS and PURCHASES. | I72: Pass | K72: Exceeds doc section 6, which asks only for requested vs approved vs funded.
A73: FL-03 | B73: §6 | C73: Fund logging | D73: Inv. Manager | E73: Functional | F73: On a 50,000 approved request, log 30,000 | G73: Partial funding accepted; remaining 20,000 shown. | H73: Logged 30,000 against an approved 99,000. Status became 'Partly funded', Funded 30,000.00, Unspent 30,000.00. | I73: Pass
A74: FL-04 | B74: §6 | C74: Fund logging | D74: Inv. Manager | E74: Functional | F74: Log a further 20,000 against the same request | G74: Fundings accumulate to 50,000; request shows fully funded. | H74: Logged a second tranche of 20,000. Funded accumulated to 50,000.00 and both receipts are listed with their own references. | I74: Pass
A75: FL-05 | B75: §6 | C75: Fund logging | D75: Inv. Manager | E75: Calculation | F75: Verify the outstanding balance after each partial funding | G75: Balance = approved − sum(funded), correct to 2 decimals. | H75: Balances reconcile at every step: Funded 50,000.00, Unspent 50,000.00 against Approved 99,000.00. | I75: Pass
A76: FL-06 | B76: §6 | C76: Fund logging | D76: Inv. Manager | E76: Negative | F76: Attempt to log 60,000 against a 50,000 approved request | G76: Blocked or explicitly warned. Over-funding must not pass silently. | H76: Attempted 150,000 against an approved 99,000. Blocked - no receipt created. | I76: Pass | J76: Medium | K76: Correctly blocked, but the only feedback is a toast reading 'Please correct the highlighted fields' with NO field highlighted and no reason given. See AA-01.
A77: FL-07 | B77: §6 | C77: Fund logging | D77: Inv. Manager | E77: Negative | F77: Attempt to log a negative funding amount | G77: Blocked. | H77: Attempted -5,000. Blocked, no receipt created. | I77: Pass | J77: Medium | K77: Same unhelpful feedback as FL-06 - see AA-01.
A78: FL-08 | B78: §6 | C78: Fund logging | D78: Inv. Manager | E78: Negative | F78: Attempt to log funds against a request still Awaiting approval | G78: Blocked — funding should follow approval. | H78: Structurally prevented. 'Record money received' only appears after the requisition has been approved, BOM'd and sent to Accounts. REQ-000007 (still at IM review) offers no funding action at all. | I78: Pass
A79: FL-09 | B79: §6 | C79: Fund logging | D79: Inv. Manager | E79: Negative | F79: Attempt to log funds against a Rejected request | G79: Blocked. | H79: Structurally prevented - a rejected requisition exposes no money panel. | I79: Pass
A80: FL-10 | B80: §6 | C80: Fund logging | D80: Inv. Manager | E80: Functional | F80: Review the funding history on a partially funded request | G80: Each tranche listed with amount, date and who logged it. | H80: RECEIPTS lists each tranche with amount, reference and date received. | I80: Pass | K80: Does not show which user logged the receipt - worth adding for an auditable money trail.
A81: FL-11 | B81: §6 | C81: Fund logging | D81: Inv. Manager | E81: Edge | F81: Log 0 as a funding amount | G81: Rejected or no-op; must not create an empty tranche. | I81: Not run
A82: FL-12 | B82: §6 | C82: Fund logging | D82: Inv. Manager | E82: Functional | F82: Confirm no automatic notification fires when a remaining tranche is logged | G82: Matches doc §6 — manual check-back is the intended design, not a defect. | H82: Confirmed - no notification is raised when a further tranche is logged, matching doc section 6's intended manual check-back. | I82: Pass
A83: IV-01 | B83: §7 | C83: Inventory | D83: Inv. Manager | E83: Functional | F83: Add a purchased laptop to inventory | G83: Storage ID auto-assigned in the LAP-nnnn pattern. | I83: Not run
A84: IV-02 | B84: §7 | C84: Inventory | D84: Inv. Manager | E84: Functional | F84: Add a second laptop | G84: Storage ID increments and is unique; no collision with existing IDs. | I84: Not run
A85: IV-03 | B85: §7 | C85: Inventory | D85: Inv. Manager | E85: Functional | F85: Enter a location manually for a stored item | G85: Free-text location saved against the item. | H85: Locations are a structured register (Meta / 1A, Meta / 1B, Meta / 2A, Nvidia / 3C, Nvidia / 4D) selected from a dropdown, not free text. | I85: Observation | K85: Doc section 7 says 'manually entered location'. The build is better - update the doc.
A86: IV-04 | B86: §7 | C86: Inventory | D86: Inv. Manager | E86: Functional | F86: Change that item's location to a new value | G86: Change accepted. | H86: Moved 2 units from Meta / 1A to Meta / 2A with a note. Meta / 1A went 5 -> 3, Meta / 2A 0 -> 2, totals unchanged. | I86: Pass
A87: IV-05 | B87: §7 | C87: Inventory | D87: Inv. Manager | E87: Functional | F87: Open the item's location history | G87: Previous and new location listed with timestamp and the user who moved it. | H87: Movement log records type, quantity, from -> to compartments, note, actor and timestamp for every event (Received, Issued, Returned, Moved). | I87: Pass | K87: Full provenance. Exceeds the requirement.
A88: IV-06 | B88: §7 | C88: Inventory | D88: Inv. Manager | E88: Functional | F88: Confirm Laptops and R&D Hardware are movable/trackable | G88: Both categories support location tracking. | H88: Laptops and R&D Hardware both carry 'Track stock for this category'. | I88: Pass
A89: IV-07 | B89: §7 | C89: Inventory | D89: All | E89: Functional | F89: Check the Furniture row (FRN-0001 Office chair) | G89: Status reads 'Not tracked', consistent with doc §7. | H89: FRN-0001 Office chair shows status 'Not tracked', matching doc section 7. | I89: Pass
A90: IV-08 | B90: §7 | C90: Inventory | D90: All | E90: Functional | F90: Filter by each category in turn | G90: Filter returns only matching rows. | H90: Category dropdown present on the inventory list with all four categories. | I90: Pass
A91: IV-09 | B91: §7 | C91: Inventory | D91: All | E91: Functional | F91: Toggle 'In stock only' | G91: Only items with Available > 0 listed. | I91: Not run
A92: IV-10 | B92: §7 | C92: Inventory | D92: All | E92: Functional | F92: Toggle 'Show archived' | G92: Archived items appear; hidden again when toggled off. | I92: Not run
A93: IV-11 | B93: §7 | C93: Inventory | D93: All | E93: Functional | F93: Search by Storage ID (LAP-0001) and by name fragment ('ThinkPad') | G93: Both return the expected row. | H93: Not executed. | I93: Not run
A94: IV-12 | B94: §7 | C94: Inventory | D94: All | E94: Calculation | F94: Compare Available against Total owned − In project use for every row | G94: Arithmetic correct on all rows. | H94: All 4 rows correct: 10-0=10, 4-0=4, 0-0=0, 55-0=55. After borrowing 2, Available correctly moved to 8 with Reserved 2. | I94: Pass
A95: IV-13 | B95: §7 | C95: Inventory | D95: Inv. Manager | E95: Functional | F95: Attempt to edit a recorded stock movement | G95: Blocked — page states 'Every movement is recorded and cannot be edited afterwards'. | H95: No edit control is offered on any recorded movement; the inventory header states movements cannot be edited afterwards. | I95: Pass | K95: Consistent with doc section 7.
A96: IV-14 | B96: §7, §11 | C96: Inventory | D96: Admin | E96: Functional | F96: Check whether the trackable-category list is configurable | G96: Extendable without a code change (doc §11 open item). Record as gap if hardcoded. | H96: The Categories screen exposes a per-category 'Track stock for this category' toggle plus 'New category' and 'Deactivate'. Furniture is set to 'Not tracked'. | I96: Pass | K96: Fully satisfies the doc section 11 open item - trackable categories are configurable, no code change needed.
A97: IV-15 | B97: §7 | C97: Inventory | D97: Inv. Manager | E97: Negative | F97: Enter a duplicate Storage ID manually, if the field is editable | G97: Rejected — Storage IDs must be unique. | I97: Not run
A98: IV-16 | B98: §7 | C98: Inventory | D98: Inv. Manager | E98: Functional | F98: Trace a funded request through to inventory | G98: Purchased items from the request can be logged into stock and linked back to the requisition. | H98: The requisition lifecycle continues past Funded into Purchased, Verified and In stock, with a PURCHASES section on the requisition, so the link from funded requisition to received inventory is modelled. | I98: Observation | K98: Purchased/Verified/In stock stages not exercised in this session.
A99: RT-01 | B99: §8 | C99: Returns | D99: General | E99: Functional | F99: Borrow an available product from Products | G99: Appears in My borrowings with the correct status. | H99: Borrowed 2 x Lenovo ThinkPad T14 from Meta / 1A. BR-000001 created with status Pending, awaiting Inventory Manager review. | I99: Pass
A100: RT-02 | B100: §8 | C100: Returns | D100: Inv. Manager | E100: Functional | F100: Log the borrowed item as returned | G100: Item logged back into storage. | H100: Approved BR-000001 (status Pending -> Out, 'Approved and issued'), then recorded a return. | I100: Pass
...

Sheet Defect Log
A1: Defect ID | B1: Linked Test ID | C1: Req Ref | D1: Title | E1: Steps to Reproduce | F1: Expected | G1: Actual | H1: Severity | I1: Priority | J1: Screenshot / Evidence | K1: Status | L1: Fixed In (commit)
A2: D-014 | B2: XX-01, XX-02 | C2: Sec 3, 5, 8 | D2: Every date field is stored one day earlier than entered, cumulatively | E2: 1. New requisition, set Approval deadline = 2026-08-20, submit/save. 2. Reopen the draft: field reads 2026-08-19. 3. Set 2026-08-25, Save draft. 4. List now shows 2026-08-24. 5. Same in Borrow: Expected back 2026-08-27 saved as 2026-08-26. | F2: The stored date equals the entered date. | G2: Every date shifts back one day, and shifts again on each save. Reproduced in both requisitions and borrowings. | H2: Critical | I2: P1 | J2: REQ-000002, BR-000001 | K2: Fixed | L2: 532a4ba
A3: D-001 | B3: AP-01, AP-05 | C3: Sec 4 | D3: No below-threshold requisition can be submitted at all | E3: 1. Create a requisition totalling under 15,000 BDT. 2. Press Submit for approval. | F3: Request routes to exactly 1 approver per doc section 4. | G3: Rejected: 'No approver is set for requests below the expense threshold.' ROOT CAUSE: the 'Sub-threshold approver' setting was 'Not assigned'. After assigning it, a 10,000 requisition submitted correctly with 1 approver (REQ-000009). This is a CONFIGURATION gap, not a code defect - but the system shipped in a state where no small purchase could be made, and the failure only surfaces after the user has filled in the whole form. | H3: Medium | I3: P2 | J3: REQ-000002, REQ-000004 | K3: Fixed | L3: pre-existing
A4: D-007 | B4: AP-03 | C4: Sec 4 | D4: Requests at exactly the threshold get 2 approvers, but the doc says 'above' | E4: 1. Submit a requisition for exactly 15,000.00 BDT. | F4: 1 approver, since 15,000 is not above 15,000. | G4: RECLASSIFIED - not a code defect. Admin Settings states 'Requisitions AT OR ABOVE this amount need the higher number of approvers', so >= is the intended product rule. The requirements doc's wording ('above the threshold') is what disagrees. | H4: Low | I4: P4 | J4: REQ-000003 | K4: Not a defect
A5: D-003 | B5: RF-N08 | C5: Sec 3, 5 | D5: A past approval deadline is accepted and the request is created already Overdue | E5: 1. New requisition, set Approval deadline to a date in the past (2026-08-01). 2. Submit. | F5: Blocked - the field's own helper text says 'Pick today or later'. | G5: Submitted as REQ-000006 and immediately tagged 'Overdue'. The section 5 reminder flow can be triggered at the moment of submission. | H5: Medium | I5: P2 | J5: REQ-000006 | K5: Fixed | L5: f9d8bc0
A6: D-002 | B6: RF-08 | C6: Sec 3 | D6: The item catalogue picker does not exist | E6: 1. New requisition. 2. Type 'Lenovo' or 'Think' in the Item field (both match catalogue stock). | F6: Matching catalogue items are offered for selection. | G6: No suggestions. The DOM shows a plain text input with autocomplete='off', no datalist and no combobox role. Every requisition line is therefore free text with no link to inventory. | H6: Medium | I6: P2 | J6: - | K6: Fixed | L6: a6c1355 + f9d8bc0
A7: D-016 | B7: XX-04 | C7: Sec 3 | D7: Draft requisitions report Requested and Sanctioned as 0 despite costed line items | E7: 1. Open draft REQ-000002. | F7: Requested = 10,000 (7,500 + 2,000 items + 500 transport). | G7: REQUESTED 0 and SANCTIONED 0 shown on the detail page and in the list, directly above a line-item table totalling 10,000. | H7: Medium | I7: P2 | J7: REQ-000002, REQ-000004 | K7: Fixed | L7: 67d8397
A8: D-015 | B8: XX-03 | C8: Sec 3 | D8: A rejected submission silently becomes a draft and consumes a reference number | E8: 1. Submit a below-threshold requisition. 2. Observe only the approver error toast. 3. Open My requisitions. | F8: Either no record is created, or the user is told a draft was saved. | G8: A draft is created (REQ-000002, REQ-000004) and a reference number is consumed, with no indication to the user. | H8: Medium | I8: P3 | J8: REQ-000002, REQ-000004 | K8: Fixed | L8: f9d8bc0
A9: D-004 | B9: RF-11 | C9: Sec 3 | D9: The draft edit form does not repopulate Department and Project | E9: 1. Save a draft with Department = Engineering and Project = Test. 2. Press Edit. | F9: Both dropdowns show the saved values. | G9: Both show 'No department' / 'No project', while the record header still reads 'Gina General - Engineering - Test'. Values survive a save, so this is display-only - but it misleads the editor. | H9: Medium | I9: P3 | J9: REQ-000002 | K9: Fixed | L9: 2bb58d2
A10: D-006 | B10: RF-N12 | C10: Sec 3, 5 | D10: Department, Project, Reason and Approval deadline are all optional | E10: 1. New requisition with only an item line, quantity and price. 2. Submit. | F10: Per doc section 3 these are request-level fields; the deadline drives section 5. | G10: REQ-000003 submitted with none of them. A requisition with no deadline can never trigger the section 5 reminder. | H10: Medium | I10: P3 | J10: REQ-000003 | K10: Fixed | L10: 8ab180d
A11: D-013 | B11: AC-08, XX-08 | C11: Sec 2 | D11: Server-side per-role authorisation is unverified | E11: 1. UI routes correctly return 'Not allowed'. 2. Unauthenticated API GETs correctly return 401. | F11: Restricted endpoints reject an authenticated user who lacks the role. | G11: Not established. UI-level blocking and anonymous rejection both work, but whether the API enforces roles for an authenticated low-privilege session was not tested - it needs an API client and explicit authorisation. | H11: Medium | I11: P2 | J11: - | K11: Not reproduced | L11: 749722a
A12: D-017 | B12: XX-05 | C12: Sec 3 | D12: Totals are computed and displayed from invalid input | E12: 1. Enter Quantity -5 and Unit price -1000. | F12: No total shown while the line is invalid. | G12: Line total and Total display 5,000.00 (negative x negative). Likewise 99,999,999,999 is totalled and displayed before being rejected on submit. | H12: Low | I12: P3 | J12: - | K12: Fixed | L12: 2bb58d2
A13: D-005 | B13: RF-N01, UX-04 | C13: UI | D13: A raw validation-library string is shown to the user | E13: 1. Submit an empty requisition form. | F13: A human-readable message such as 'Required'. | G13: The Item field shows 'String must contain at least 1 character(s)' while the adjacent fields correctly show 'Required'. | H13: Low | I13: P3 | J13: - | K13: Fixed | L13: a44050f
A14: D-019 | B14: XX-07 | C14: UI | D14: Requisition list re-sorts by last-updated with no sort indicator | E14: 1. Edit and save an older draft. 2. Return to My requisitions. | F14: Order is stable or the sort is indicated. | G14: The edited row jumps to the top. Headers show no sort state and are not clickable. | H14: Low | I14: P4 | J14: - | K14: Fixed | L14: d4a3864
A15: D-009 | B15: UX-01 | C15: UI | D15: Dashboard copy says live modules 'arrive in later phases' | E15: 1. Open the Dashboard as any user. | F15: Copy reflects the current build. | G15: Reads 'Inventory, borrowing, requisitions and BOM arrive in later phases' although all four are live. | H15: Cosmetic | I15: P4 | J15: - | K15: Fixed | L15: 6ab88f9
A16: D-011 | B16: UX-06 | C16: UI | D16: Three different date formats across the application | E16: 1. Compare My requisitions, Projects and a requisition History panel. | F16: One consistent format. | G16: 2026-08-13 / Aug 12, 2026 / 8/13/2026, 1:57:26 PM. | H16: Cosmetic | I16: P4 | J16: - | K16: Fixed | L16: 7c740db
... A32: D-032 | B32: BB-03 | C32: UI | D32: A raw config constant is exposed as a settings label | E32: 1. Open Admin > Settings. 2. Read the third setting. | F32: A human-readable label and help text. | G32: Labelled 'BOM_OVER_BUDGET_TOLERANCE_PCT' with no description, unlike every other setting on the page. | H32: Low | I32: P4 | J32: Admin Settings | K32: Fixed | L32: 9c562a1

Sheet Test Data & Cleanup
A1: Test data created during this QA session
A2: All records created by QA are prefixed QA-TEST- so they can be identified and removed.
A4: # | B4: Record type | C4: Reference / ID | D4: Created as role | E4: Purpose | F4: Cleanup action required
A5: 1 | B5: Requisition | C5: REQ-000002 | D5: General | E5: Blocked below-threshold submit, auto-saved as draft (10,000) | F5: Delete draft
A6: 2 | B6: Requisition | C6: REQ-000003 | D6: General | E6: Threshold boundary test at exactly 15,000 | F6: Cancel / delete - currently With the Inventory Manager
A7: 3 | B7: Requisition | C7: REQ-000004 | D7: General | E7: Blocked below-threshold submit at 14,999, auto-saved as draft | F7: Delete draft
A8: 4 | B8: Requisition | C8: REQ-000005 | D8: General | E8: Transport threshold discriminator (14,800 + 300) | F8: Cancel / delete - currently With the Inventory Manager
A9: 5 | B9: Requisition | C9: REQ-000006 | D9: General | E9: Past-deadline test (20,000, deadline 2026-08-01, Overdue) | F9: Cancel / delete - currently With the Inventory Manager
A10: 6 | B10: Requisition | C10: REQ-000007 | D10: General | E10: Output-encoding test, item named <b>QA-TEST-Encoding</b> (20,000) | F10: Cancel / delete - currently With the Inventory Manager
A11: 7 | B11: Borrowing | C11: BR-000001 | D11: General | E11: Borrow test, 2 x Lenovo ThinkPad T14 from Meta / 1A | F11: Cancel request, or approve then return, to release the 2 reserved units
A12: 8 | B12: Requisition state | C12: REQ-000003 | D12: Inv. Manager | E12: IM-approved during testing; now Awaiting approval | F12: Cancel or leave; note it is QA data
A13: 9 | B13: Requisition state | C13: REQ-000005 | D13: Inv. Manager | E13: IM-approved during testing; now Awaiting approval | F13: Cancel or leave; note it is QA data
A14: 10 | B14: Requisition state | C14: REQ-000006 | D14: Inv. Manager | E14: IM-rejected during testing (rejection-path test) | F14: No action - terminal state
A15: 11 | B15: Stock movement | C15: LAP-0001 | D15: Inv. Manager | E15: Issued 2, returned 1 Damaged to Nvidia / 3C, moved 2 from Meta / 1A to Meta / 2A | F15: 1 unit sits in QUARANTINE at Nvidia / 3C and needs releasing; 1 unit still out on BR-000001
A16: 12 | B16: Borrowing | C16: BR-000001 | D16: Inv. Manager | E16: Borrow lifecycle test, now Partly returned | F16: Return the remaining 1 unit to close it out
... A28: 24 | B28: Requisition | C28: REQ-000013 | D28: General | E28: QA-TEST-D014-DATESHIFT — date-shift reproduction, 20 Aug 2026. Deadline entered 2026-08-27, stored 2026-08-26, re-saved without editing the field, now 2026-08-25. One item at 1.00. | F28: Delete draft. Created by the dev team to reproduce D-014, not by the QA session.
